dhl_express/__init__.py
dhl_express/dhl.py
dhl_express-0.2.1.dist-info/METADATA
dhl_express-0.2.1.dist-info/WHEEL
dhl_express-0.2.1.dist-info/top_level.txt
dhl_express-0.2.1.dist-info/RECORD
