Metadata-Version: 2.1
Name: dhl-express
Version: 0.2.1
Summary: A Python library for interacting with DHL Express API
Home-page: https://github.com/DCDie/dhl-express
Author: Daniel Cuznetov
Author-email: danielcuznetov04@gmail.com
Project-URL: Bug Tracker, https://github.com/DCDie/dhl-express/issues
Classifier: Programming Language :: Python :: 3
Classifier: License :: OSI Approved :: Apache Software License
Classifier: Operating System :: OS Independent
Requires-Python: >=3.8
